pyfetch_mimic.py
pyfetch_mimic-2024.6.14.dist-info/LICENSE
pyfetch_mimic-2024.6.14.dist-info/METADATA
pyfetch_mimic-2024.6.14.dist-info/WHEEL
pyfetch_mimic-2024.6.14.dist-info/top_level.txt
pyfetch_mimic-2024.6.14.dist-info/RECORD
