Metadata-Version: 2.1
Name: pyfetch_mimic
Version: 2024.6.14
Summary: This is a module that mimics pyodide.http.pyfetch to enable simpler development by using one set of http calls for both local and pyodide executions.
Author-email: darrida <darrida.py@gmail.com>
Project-URL: Homepage, https://github.com/darrida/py-shinylive-pyfetch-mimic
Project-URL: Issues, https://github.com/darrida/py-shinylive-pyfetch-mimic/issues
Classifier: Programming Language :: Python :: 3
Classifier: License :: OSI Approved :: MIT License
Classifier: Operating System :: OS Independent
License-File: LICENSE
Requires-Dist: shiny
Requires-Dist: httpx
Provides-Extra: tests
Requires-Dist: fastapi ; extra == 'tests'
Requires-Dist: pytest ; extra == 'tests'
Requires-Dist: pytest-asyncio ; extra == 'tests'
Requires-Dist: robotframework ; extra == 'tests'
Requires-Dist: robotframework-dependencylibrary ; extra == 'tests'
Requires-Dist: robotframework-pythonlibcore ; extra == 'tests'
Requires-Dist: robotframework-seleniumlibrary ; extra == 'tests'
Requires-Dist: robotframework-stacktrace ; extra == 'tests'
Requires-Dist: selenium ; extra == 'tests'
Requires-Dist: seleniumbase ; extra == 'tests'
Requires-Dist: coverage ; extra == 'tests'
Requires-Dist: shinylive ; extra == 'tests'
